temlogger/__init__.py
temlogger/helpers.py
temlogger/temlogger.py
temlogger/providers/__init__.py
temlogger/providers/base.py
temlogger/providers/console.py
temlogger/providers/default.py
temlogger/providers/logstash.py
temlogger/providers/stackdriver.py
temlogger/tests/__init__.py
temlogger/tests/base.py
temlogger/tests/test_formatters.py
temlogger/tests/test_get_loggers.py
temlogger/tests/test_helpers.py
temlogger/tests/test_logging_config.py
temlogger/tests/test_setup_event_handlers.py
temlogger-0.5.0.dist-info/LICENSE
temlogger-0.5.0.dist-info/METADATA
temlogger-0.5.0.dist-info/WHEEL
temlogger-0.5.0.dist-info/top_level.txt
temlogger-0.5.0.dist-info/RECORD
