Metadata-Version: 2.1
Name: temlogger
Version: 0.5.0
Summary: Python logging handler for Logstash and StackDriver.
Home-page: https://github.com/tembici/temlogger
Author: Nielson Santana
Author-email: nielsonnas@gmail.com
License: MIT
Platform: UNKNOWN
Classifier: Development Status :: 4 - Beta
Classifier: Intended Audience :: Developers
Classifier: License :: OSI Approved :: MIT License
Classifier: Operating System :: OS Independent
Classifier: Programming Language :: Python :: 3
Classifier: Topic :: Internet :: WWW/HTTP
Classifier: Topic :: Software Development :: Libraries :: Python Modules
Classifier: Topic :: System :: Logging
Requires-Dist: google-cloud-logging (<2,>=1.14.0)
Requires-Dist: python3-logstash (==0.4.80)
